statwrap/__init__.py
statwrap/atus.py
statwrap/core.py
statwrap/data.py
statwrap/exceptions.py
statwrap/fpp.py
statwrap/mlp.py
statwrap/sheets.py
statwrap/utils.py
statwrap/ux.py
statwrap/visualization.py
statwrap-0.3.1.dist-info/licenses/LICENSE
tests/__init__.py
tests/test_exceptions.py
tests/test_fpp.py
tests/test_sheets.py
tests/test_utils.py
tests/test_visualization.py
statwrap-0.3.1.dist-info/METADATA
statwrap-0.3.1.dist-info/WHEEL
statwrap-0.3.1.dist-info/top_level.txt
statwrap-0.3.1.dist-info/RECORD
