Metadata-Version: 2.4
Name: StatWrap
Version: 0.3.1
Summary: A package for people new to statistics and Python.
Home-page: https://github.com/alexanderthclark/statwrap
Author: Alexander Clark
Author-email: 
Project-URL: Documentation, https://statwrap.readthedocs.io/
License-File: LICENSE
Requires-Dist: pandas
Requires-Dist: numpy
Requires-Dist: scipy
Requires-Dist: IPython
Requires-Dist: matplotlib
Requires-Dist: statsmodels
Requires-Dist: scikit-learn
Requires-Dist: ipywidgets==7.7.1
Requires-Dist: odfpy
Requires-Dist: openpyxl
Dynamic: author
Dynamic: description
Dynamic: description-content-type
Dynamic: home-page
Dynamic: license-file
Dynamic: project-url
Dynamic: requires-dist
Dynamic: summary
